{
    "page_url": "https://steamrip.com/100-orange-juice-free-download/",
    "title": "100 % Orange Juice",
    "description": "100% Orange Juice is a digital multiplayer board game populated by developer Orange Juice’s all-star cast. Characters from Flying Red Barrel, QP Shooting , Suguri and Sora come together with all-new characters to duke it out with dice. Quilts and Cats of Calico\nThis is a world where dogs , people and machines fly through the air. In that world, a small patch of darkness was born. Infinitesimal at first, it gradually began to envelop everything A youth named Kai, led by the mysterious life form known as Marie Poppo , begins a journey that will span worlds. The black, bottomless darkness of desire slowly eats away at both Kai and the world itself. Let Marie Poppo lead you into a mysterious world to play. Grab your deck of cards and let the games begin",
    "screenshots": [
        "https://steamrip.com/wp-content/uploads/2024/03/100-orange-game-juice-steamrip.jpg",
        "https://steamrip.com/wp-content/uploads/2024/03/100-orange-game-juice-screenshots-steamrip.jpg"
    ],
    "system_requirements": {
        "OS": "Windows 10/11",
        "Processor": "Intel Pentium 2.0GHz or higher",
        "Memory": "1024 MB RAM",
        "Graphics": "Direct3D compatible video card with 128MB memory or more",
        "DirectX": "Version 9.0c",
        "Network": "Broadband Internet connection",
        "Storage": "1 GB available space"
    },
    "game_info": {
        "Genre": "Indie, Strategy",
        "Developer": "Orange_Juice",
        "Platform": "PC",
        "Game Size": "1.7 GB",
        "Released By": "Mr_GOLDBERG",
        "Version": "Build 13623225 | Full  + All DLCs",
        "Pre-Installed Game": ""
    },
    "download_links": [
        "https://megadb.net/1b8savf8mhfs"
    ],
    "cover_image": "https://steamrip.com/wp-content/uploads/2024/03/100-orange-game-juice-preinstalled-steamrip.jpg"
}