{
    "page_url": "https://steamrip.com/20-minutes-till-dawn-free-download-n1/",
    "title": "20 Minutes Till Dawn",
    "description": "Survive the onslaught of an endless horde of monsters for 20 minutes In this roguelite survival game, select from a variety of upgrades to create a unique and overpowered builds every run. You can be a fire wizard, for example, and ignite monsters with every pump of your shotgun, or an agile ninja who controls magic knives to pierce your enemies. Choose from a diverse selection of characters and weapons that offer a variety of gameplay experiences. Resident Evil 4 Ultimate HD Edition",
    "screenshots": [
        "https://steamrip.com/wp-content/uploads/2022/06/20-minutes-till-dawn-steamrip.jpg",
        "https://steamrip.com/wp-content/uploads/2022/06/20-minutes-till-dawn-screenshots-steamrip.jpg"
    ],
    "system_requirements": {
        "OS": "Windows 7",
        "Processor": "Dual Core+",
        "Memory": "1 GB RAM",
        "Graphics": "1 GB RAM",
        "Storage": "100 MB available space"
    },
    "game_info": {
        "Genre": "Action, Adventure, Casual, Indie, Strategy",
        "Developer": "flanne",
        "Platform": "PC",
        "Game Size": "91 MB",
        "Released By": "N/A",
        "Version": "v1.0.2 | Full",
        "Pre-Installed Game": ""
    },
    "download_links": [
        "https://megadb.net/z4hr8kfphjqt"
    ],
    "cover_image": "https://steamrip.com/wp-content/uploads/2022/06/20-minutes-till-dawn-preinstalled-steamrip.jpg"
}