{
    "page_url": "https://steamrip.com/assassins-creed-free-download-5m/",
    "title": "Assassin’s Creed Free",
    "description": "Get Assassin’s Creed PC game for free instantly and play pre-installed on SteamRiP\nAssassin’s Creed is the next-gen game developed by Ubisoft Montreal that redefines the action genre. While other games claim to be next-gen with impressive graphics and physics, Assassin’s Creed merges technology, game design, theme and emotions into a world where you instigate chaos and become a vulnerable, yet powerful , agent of change. The setting is 1191 AD.\nThe Third Crusade is tearing the Holy Land apart. You, Altair, intend to stop the hostilities by suppressing both sides of the conflict. You are an Assassin, a warrior shrouded in secrecy and feared for your ruthlessness. Your actions can throw your immediate environment into chaos, and your existence will shape events during this pivotal moment in history. Baldo: The Guardian Owls",
    "screenshots": [
        "https://steamrip.com/wp-content/uploads/2021/08/assassins-creed-free-download-steamrip.jpg",
        "https://steamrip.com/wp-content/uploads/2021/08/assassins-creed-free-download-crack-steamrip.jpg"
    ],
    "system_requirements": {
        "Processor": "Dual core processor 2.6 GHz Intel® Pentium® D",
        "System Memory": "Windows XP: 1 GB RAM / Windows Vista: 2 GB RAM",
        "Video Card": "256 MB DirectX® 10.0-compliant video card",
        "Sound Card": "DirectX 9.0 or 10.0-compliant sound card (5.1 sound card recommended)",
        "DirectX Version": "Direct X 9.0 (Windows XP) or 10.0 (Windows Vista) libraries",
        "Hard Disk": "8 GB available hard disk space"
    },
    "game_info": {
        "Genre": "Action, Adventure",
        "Developer": "Ubisoft Montreal",
        "Platform": "PC",
        "Game Size": "4.45 GB",
        "Repack By": "N/A",
        "Version": "Full",
        "Pre-Installed Game": ""
    },
    "download_links": [
        "https://buzzheavier.com/t4lbtz4eekkr",
        "https://megadb.net/mkv74ofl1czf",
        "https://datanodes.to/yzxu09xnfhnx/Assassins-Creed-SteamRIP.com.rar"
    ],
    "cover_image": "https://steamrip.com/wp-content/uploads/2021/08/assassins-creed-free-download-preinstalled-steamrip.jpg"
}