{
    "page_url": "https://steamrip.com/bang-on-balls-chronicles-free-download-j1/",
    "title": "Bang-On Balls: Chronicles Free Download",
    "description": "Glorious bouncy 3D platforming and combat inspired by some of the best in the genre from Italian plumbers, blue hedgehogs, or wild bandicoots! Become BOB, a reckless bouncy hero embarking on a quest of epic adventures and chaos. Land of the Vikings\nRoll into jam-packed open worlds that let you explore and utterly smash them to pieces in the process! Conquer adversaries and boss fights, tackle thrilling challenges, and unearth multiple hidden secrets. Realms bursting with activities to do at your own pace while you break almost everything along the way.\nBounce between multiple (slightly inaccurate) historically themed open worlds each with their own unique mechanics, items, and enemies. From the Vikings through to the Age of Pirates. From Feudal Japan over into The Space Race. Each world lets you hop in and out whenever and carry over progress.\nGo solo or grab friends. Supports single player, 2-player split screen, and online co-op up to 4 players! Jump in and out sessions and keep any items and weapons collected.",
    "screenshots": [
        "https://steamrip.com/wp-content/uploads/2023/10/bang-on-balls-chronicles-steamrip.jpg",
        "https://steamrip.com/wp-content/uploads/2023/10/bang-on-balls-chronicles-screenshots-steamrip.jpg"
    ],
    "system_requirements": {
        "OS": "Windows 10",
        "Processor": "AMD Ryzen™ 3 1200 / Intel® Core™ i3-8100",
        "Memory": "6 GB RAM",
        "Graphics": "NVIDIA® GeForce® GTX 660 2GB / AMD Radeon™ HD 7850 2GB",
        "DirectX": "Version 11",
        "Network": "Broadband Internet connection",
        "Storage": "3 GB available space"
    },
    "game_info": {
        "Genre": "Action, Adventure, Casual, Indie",
        "Developer": "Exit Plan Games",
        "Platform": "PC",
        "Game Size": "3.8 GB",
        "Co-op By": "0xdeadc0de",
        "Version": "Build 05102023 | Full",
        "Pre-Installed Game": ""
    },
    "download_links": [
        "https://megadb.net/a9lx1o8sllcu"
    ],
    "cover_image": "https://steamrip.com/wp-content/uploads/2023/10/bang-on-balls-chronicles-preinstalled-steamrip.jpg"
}