{
    "page_url": "https://steamrip.com/case-00-the-cannibal-boy-free-download-1l/",
    "title": "Case 00 The Cannibal Boy",
    "description": "Case 00: The Cannibal Boy is a half-hour visual novel partly based on a true story, written by a writer with a background in psychology. It is a psychological horror story with an urban legend theme. Have you heard of the “Cannibal Boy”? If you’ve heard his story, you have to hurry and tell someone who hasn’t. Or else, he might just come get YOU Characters A master’s student in psychology . Choo Choo Survivor\nThe topic of your master’s thesis is “judgment and decision making.  An interning psychologist. She is constantly smiling but her eyes always look shut. “Eating is essentially a kind of possession , a kind of intimacy, just like having sex.” A grad student who enjoys college life. He sometimes worries about whether he will find a decent job. “It’s the urban legend everyone’s been talking about” Jade’s BFF. She has a tendency to be passive aggressive and jumps to conclusions. “Your fault your fault your fault your fault your fault”",
    "screenshots": [
        "https://steamrip.com/wp-content/uploads/2023/10/case-00-the-cannibal-boy-steamrip.jpg",
        "https://steamrip.com/wp-content/uploads/2023/10/case-00-the-cannibal-boy-screenshots-steamrip.jpg"
    ],
    "system_requirements": {
        "OS": "Windows 7",
        "Processor": "Intel Core 2 DUO 2.4 GHz / AMD Athlon X2 2.7 GHz",
        "Memory": "8 GB RAM",
        "Graphics": "Nvidia GTX 650 Ti or AMD HD 7850",
        "Storage": "7 GB available space"
    },
    "game_info": {
        "Genre": "Adventure, Casual, Indie",
        "Developer": "Sounding Stone / 老奉毊, Meijin Zhu / 五月梅花落, MaouCat Studio / 魔王貓工作室",
        "Platform": "PC",
        "Game Size": "294 MB",
        "Released By": "Mr_GOLDBERG",
        "Version": "v1.02 | Full",
        "Pre-Installed Game": ""
    },
    "download_links": [
        "https://megadb.net/rkbld2ieihnq"
    ],
    "cover_image": "https://steamrip.com/wp-content/uploads/2023/10/case-00-the-cannibal-boy-preinstalled-steamrip.jpg"
}