{
    "page_url": "https://steamrip.com/disney-infinity-3-0-gold-edition-free-download/",
    "title": "Disney Infinity 3.0: Gold Edition",
    "description": "Disney Infinity 3.0: Gold Edition includes Star Wars to the ever-growing collection of Marvel , Disney and Disney Pixar characters, stories and worlds NOW with all Disney Infinity Characters and Playsets Unlocked. Together new heroes can join forces with all other Disney Infinity characters and embark on adventures as big as your imagination in the 3.0 Toy Box! Disney Infinity encourages you to play your way, whether you explore open-world creation in the Toy Box or story-driven gameplay inside Play Sets\nA ll Disney Infinity 3.0 Playsets Unlocked:\nAll Disney Infinity 3.0 Characters Unlocked\nEnjoy Disney Infinity with a Full Toy Box",
    "screenshots": [
        "https://steamrip.com/wp-content/uploads/2025/02/disney-infinity-3-gold-edition-steamrip.jpg",
        "https://steamrip.com/wp-content/uploads/2025/02/disney-infinity-3-gold-edition-screenshots-steamrip.jpg"
    ],
    "system_requirements": {
        "OS": "*: Windows Vista / 7 / 8",
        "Processor": "2.2 GHz Dual-Core CPU",
        "Memory": "2 GB RAM",
        "Graphics": "Nvidia GeForce 560 / ATI Radeon HD 5600 1 GB",
        "DirectX": "Version 11",
        "Storage": "15 GB available space"
    },
    "game_info": {
        "Genre": "Action, Adventure",
        "Developer": "Avalanche Software, Heavy Iron Studios",
        "Platform": "PC",
        "Game Size": "13.3 GB",
        "Released By": "PLAZA emu",
        "Version": "Build 1522802 | Full",
        "Pre-Installed Game": ""
    },
    "download_links": [
        "https://datanodes.to/j10pb46lwsrk/Disney-Infinity-3-GE-SteamRIP.com.rar",
        "https://buzzheavier.com/jk4safeb5ppq"
    ],
    "cover_image": "https://steamrip.com/wp-content/uploads/2025/02/disney-infinity-3-gold-edition-preinstalled-steamrip.jpg"
}