{
    "page_url": "https://steamrip.com/forza-horizon-3-free-download-1i/",
    "title": "Forza Horizon 3 Free Download Direct Link",
    "description": "Forza Horizon 3 is one of the best arcade racing games in recent memory . Here you will find sunny Australia with its unusual tracks, an incredible number of cars, unrivaled graphics and much more And first of all I would like to say that if the previous parts of “Forza Horizon ” all the time “limped” due to insufficiently worked out physics, then in “ Forza Horizon 3″ this problem was solved once and for all.\nNow cars feel fine on the track, drift well in corners, have become more controllable and, in general, have finally begun to correspond to their prototypes from reality. Well, if somewhere there are mistakes in terms of physics and handling, then you will not notice them, because most of the tracks are such that they are aimed at developing speed, and not testing with cornering . The visual design of the game has moved to a fundamentally new level of quality. Now you will be driving along the roads of beautiful Australia. But the new setting is not only new roads, but also bonuses in the form of new cars and new opportunities .",
    "screenshots": [
        "https://steamrip.com/wp-content/uploads/2021/07/forza-horizon-3-free-download-steamrip.jpg",
        "https://steamrip.com/wp-content/uploads/2021/07/forza-horizon-3-free-download-crack-steamrip.jpg"
    ],
    "system_requirements": {
        "OS": "Windows 10",
        "Processor": "i7 3820 3.6GHz",
        "Memory": "12 GB",
        "Graphics": "NVIDIA GeForce GTX 750 Ti / AMD Radeon R7 250X @ 2 GB, DirectX 12",
        "DirectX": "12 API, Hardware Feature Level 11"
    },
    "game_info": {
        "Genre": "Racing, Simulation",
        "Developer": "Playground Games",
        "Platform": "PC",
        "Game Size": "60.21 GB",
        "Multiplayer By": "0xdeadc0de (online-fix.me)",
        "Repack By": "DODI Repacks (Torrent)",
        "Version": "v1.0.125.2 | Full version (Latest) + all add-ons",
        "Pre-Installed Game": ""
    },
    "download_links": [
        "https://filecrypt.co/Container/FAE6FFF874",
        "https://buzzheavier.com/3hhoaujk7oyl",
        "https://datanodes.to/14dnr3pkepph/Forza-Horizon-3-SteamRIP.com.rar",
        "https://1fichier.com/?hkyfxd58itikdj5yw2ir"
    ],
    "cover_image": "https://steamrip.com/wp-content/uploads/2021/07/forza-horizon-3-free-download-preinstalled-steamrip.jpg"
}