{
    "page_url": "https://steamrip.com/potion-craft-alchemist-simulator-free-download-1q/",
    "title": "Potion Craft: Alchemist Simulator Free Download",
    "description": "Get Potion Craft Alchemist Simulator for free instantly and play pre-installed on SteamRiP\nLeaves, flowers, berries, roots, fruits, minerals , and a plethora of mushrooms are at the ready for your mortar and pestle. Just like espresso, the fineness of the grind matters Concoct your potion plan. Grind ingredients and carefully mix them in your cauldron. Heat the coals. Boil and stir. Add the base: water, oil, or something else. Congrats on your first potion Was it easy to learn?\nNow try mastering it Carefully plan your route via the Alchemy Map to combine different effects. Be mindful of common sense: you won’t find a market for a poisonous healing potion right? Or would you? Every day customers will come to your store looking for solutions to their problems. You will face consequences depending on what you decide to sell them. Attract guilds, befriend notable figures (or feud with them), gain riches and influence – and one day, you may even decide the fate of the whole town.",
    "screenshots": [
        "https://steamrip.com/wp-content/uploads/2021/10/potion-craft-alchemist-simulator-free-download-steamrip.jpg",
        "https://steamrip.com/wp-content/uploads/2021/10/potion-craft-alchemist-simulator-free-download-screenshots-steamrip.jpg"
    ],
    "system_requirements": {
        "OS": "Windows 10",
        "Processor": "Intel i3-6100 or equivalent",
        "Memory": "8 GB RAM",
        "Graphics": "GeForce GTX 670 / Radeon HD 7970",
        "DirectX": "Version 10",
        "Storage": "5 GB available space"
    },
    "game_info": {
        "Genre": "Indie, Simulation",
        "Developer": "niceplay games",
        "Platform": "PC",
        "Game Size": "1.2 GB",
        "Released By": "CODEX emu",
        "Version": "v2.0.2.0 | Full",
        "Pre-Installed Game": ""
    },
    "download_links": [
        "https://megadb.net/b0931xza2vbm"
    ],
    "cover_image": "https://steamrip.com/wp-content/uploads/2021/10/potion-craft-alchemist-simulator-free-download-preinstalled-steamrip.jpg"
}