{
    "page_url": "https://steamrip.com/videoverse-free-download-1x/",
    "title": "VIDEOVERSE",
    "description": "Relive the days of past social gaming networks in VIDEOVERSE, a decision-based narrative adventure focusing on character development, friendship and love, from the developer behind One Night Stand. As Emmett, a young video game fan and aspiring artist, dive into this fictional video game era, where the Kinmoku Shark gaming system and its online social network, Videoverse, were still popular. Deathbulge: Battle of the Bands\nStrengthen Emmett’s friendships , share fan art and browse the lively gaming communities. Make decisions that will change how Emmett grows, his approach to Videoverse and, ultimately, the final outcome Will your actions help Videoverse thrive, or will you get caught up in teenage drama , video game fandoms and corporate conspiracies?",
    "screenshots": [
        "https://steamrip.com/wp-content/uploads/2023/08/videoverse-steamrip.jpg",
        "https://steamrip.com/wp-content/uploads/2023/08/videoverse-screenshots-steamrip.jpg"
    ],
    "system_requirements": {
        "OS": "Windows 7",
        "Processor": "Intel Celeron CPU 1000M 1.80GHz",
        "Memory": "4 GB RAM",
        "Storage": "581 MB available space"
    },
    "game_info": {
        "Genre": "Adventure, Casual, Indie, Simulation",
        "Developer": "Kinmoku",
        "Platform": "PC",
        "Game Size": "496 MB",
        "Released By": "Mr_GOLDBERG",
        "Version": "v1.0.0.2 | Full",
        "Pre-Installed Game": ""
    },
    "download_links": [
        "https://megadb.net/s2f4v72iwcsb"
    ],
    "cover_image": "https://steamrip.com/wp-content/uploads/2023/08/videoverse-preinstalled-steamrip.jpg"
}