{
    "page_url": "https://steamrip.com/wartales-free-download-1e/",
    "title": "Wartales Download",
    "description": "Get Wartales PC Game In Direct Link and play pre-installed on SteamRiP\nIt has been a hundred years since the world saw the fall of the once great Edoran Empire at the hands of an unprecedented plague that swept the nation. In the turmoil and uncertainty that has followed, mercenary work, banditry and thievery across the land is abundant , as honor has long since become an almost entirely forgotten virtue.\nNow, prepare to lead a group of unscrupulous characters who revel in such activity in a massive open world where combat, death and a thirst for riches will shape and define your day to day life. You are not special, the chosen one or a once in a millennia hero ushering in a new era of peace. Your goal is solely to survive and thrive in this harsh and hostile world. Only the bravest and most ambitious can hope to see their story written in the Wartales.",
    "screenshots": [
        "https://steamrip.com/wp-content/uploads/2021/12/wartales-free-download-steamrip.jpg",
        "https://steamrip.com/wp-content/uploads/2021/12/wartales-free-download-screenshots-steamrip.jpg"
    ],
    "system_requirements": {
        "OS": "Windows 7 64bit",
        "Processor": "Intel 2.0ghz Core 2 Duo or equivalent",
        "Memory": "2 GB RAM",
        "Graphics": "GeForce GTX 690",
        "DirectX": "Version 10",
        "Storage": "6 GB available space"
    },
    "game_info": {
        "Genre": "Adventure, Indie, RPG, Strategy",
        "Developer": "Shiro Games",
        "Platform": "PC",
        "Game Size": "14.2 GB",
        "Released By": "RUNE",
        "Version": "v1.0.41212 | Full  + All DLCs",
        "Pre-Installed Game": ""
    },
    "download_links": [
        "https://datanodes.to/rsg1tze2igsd/Wartales-SteamRIP.com.rar",
        "https://gofile.io/d/Ys70ZB",
        "https://buzzheavier.com/uy96ek266yj3"
    ],
    "cover_image": "https://steamrip.com/wp-content/uploads/2021/12/wartales-preinstalled-steamrip.jpg"
}